<?xml version="1.0" encoding="utf-8"?>
<!-- 파싱해서 사용하는 데이터이니 직접 수정하지 마세요 -->
<ms2>
	<minimap>
		<image name="./Data/Resource/Image/Map/Minimap/02000265.dds" left="352.95" right="1376.95" top="18.9" bottom="1042.9" icon="" />
		<frustum left="-7680" right="7680" top="4320" bottom="-4320" near="10" far="100000" ortho="true" />
		<screen left="0" right="1920" top="0" bottom="1080" />
		<camera position="-1015.047546, -562.052185, 5772.894043" rotation="90.000000, 45.000000, -45.000000" />
		<edit zoomfactor="4" />
	</minimap>
	<fog color="80,76,87" near="400" far="6000" />
	<heightfog color="94,120,122" upper="3497" lower="1043" percentage="100" />
	<clientProperty bgDay="BG_SF_A.dds" />
</ms2>