<?xml version="1.0" encoding="utf-8"?>
<!-- 파싱해서 사용하는 데이터이니 직접 수정하지 마세요 -->
<ms2>
	<minimap>
		<frustum left="-19456.2" right="19456.2" top="10944.1" bottom="-10944.1" near="10" far="100000" ortho="true" />
		<screen left="0" right="2560" top="0" bottom="1440" />
		<image left="858.95" right="1882.95" top="201.95" bottom="1225.95" name="./Data/Resource/Image/Map/Minimap/02000538.dds" icon="" />
		<camera position="-2681.269043, -3118.213379, 10358.271484" rotation="90.000000, 45.000000, -45.000000" />
		<edit zoomfactor="7.60008" />
	</minimap>
	<fog color="70,95,79" near="0" far="16000" />
	<heightfog color="20,95,220" upper="3600" lower="-9999" percentage="44" />
	<clientProperty bgDay="sw_bg_henesys_b.dds" />
</ms2>