<?xml version="1.0" encoding="utf-8"?>
<!-- 파싱해서 사용하는 데이터이니 직접 수정하지 마세요 -->
<ms2>
	<environment locale="KR">
		<quest>
			<basic questID="80000453" questType="2" chapterID="8136" account="2" standardLevel="10" repeatable="2" usePeriod="1440" eventTag="20180615_word4" useNavi="FALSE" />
			<require level="10" dayOfWeek="1,2,3,4,5,6,7" />
			<start npc="11001002" />
			<complete npc="11001002" />
			<completeReward>
				<essentialItem code="30001135" rank="1" count="25" />
			</completeReward>
			<condition type="item_exist" code="30001147" value="1" />
			<condition type="item_exist" code="30001148" value="1" />
			<condition type="item_exist" code="30001149" value="1" />
			<condition type="item_exist" code="30001150" value="1" />
		</quest>
	</environment>
</ms2>