<?xml version="1.0" encoding="utf-8"?>
<ms2>
  <effect type="nif" filePath="NPC/Skill/TitanFourArmsGoldMask/Eff_TitanFourArmsGoldMaskThirdFloor_Attack_01_I_CurseCenter_b.nif" startDelay="0.0" duration="2.5" viewDistance="0">
    <attachInfo attachToNode="true" applyNodeTransform="true" parentNode="Bip01 Head"></attachInfo>
    <transform translate="30.0, 70.0, -10.0" rotation="0.0, 0.0, 0.0" scale="0.6" />
  </effect>
  <effect type="nif" filePath="NPC/Skill/BalrogMagicBurster/Eff_BalrogMagicBurster_Attack_Idle_B_EyeFire.nif" startDelay="0.0" duration="2.5" viewDistance="0">
    <attachInfo attachToNode="true" applyNodeTransform="true" parentNode="Bip01 Head"></attachInfo>
    <transform translate="0.0, -30.0, 0.0" rotation="0.0, 0.0, 0.0" scale="1.3" />
  </effect>
</ms2>