<?xml version="1.0" encoding="utf-8"?>
<!-- 파싱해서 사용하는 데이터이니 직접 수정하지 마세요 -->
<ms2>
  <key id="s_DestinyofMika_01" name="Muitos dos Lumarigons anciãos corrompidos pelo Rei Demônio\nperturbaram o equilíbrio do poder em favor da escuridão conforme a vontade dele.\nAs criaturas das trevas criadas como resultado disso são chamadas de &amp;quot;Kargons&amp;quot;." npc="NotUse" />
  <key id="s_DestinyofMika_02" name="Perduraram os conflitos tribais entre os defensores da luz e da escuridão, \ne agora Drachenheim enfrenta a maior ameaça de todas." npc="NotUse" />
  <key id="s_DestinyofMika_03" name="Para proteger Mika, Layla utilizou uma magia proibida para acobertar sua fuga.\nConsequentemente, Layla perdeu todos os seus poderes como sucessora da luz." npc="NotUse" />
  <key id="s_DestinyofMika_04" name="Mika, você deve purificar a pedra-lúmen do caos\ne encontrar a fonte do poder que Layla lhe concedeu." npc="NotUse" />
  <key id="s_lumieragonhistory_01" name="Lumarigons: inteligentes, fortes e inabalavelmente virtuosos. Quando veio a escuridão,\neles entraram na batalha pela alma do Mundo Maple." npc="에레브" />
  <key id="s_lumieragonhistory_02" name="Mas esses grandes dragões não eram invencíveis. Depois que seu líder, o mestre dragão Biset,\npereceu em batalha, todos os lumarigons praticamente desapareceram." npc="에레브" />
  <key id="s_lumieragonhistory_03" name="Para se salvarem, os lumarigons escaparam para o santuário de seu povo e caíram em um sono profundo." npc="에레브" />
  <key id="s_lumieragonhistory_04" name="Dizem que quando um novo mestre dragão surgir, os lumarigons retornarão ao Mundo Maple." npc="에레브" />
  <key id="s_lumieragonhistory_05" name="Com o passar dos anos, os lumarigons se tornaram uma memória esquecida. Isto é, até o dia do cerco de Tria…" npc="에레브" />
  <key id="s_lumieragonhistory_06" name="O dragão que Madria trouxe para batalha. Seria possível que ele fosse um desses lendários lumarigons? \nTeriam eles se voltado para a escuridão?" npc="에레브" />
  <key id="s_lumieragonhistory_07" name="Se os lumarigons tiverem se unido ao inimigo, então a luz do Mundo Maple pode ser extinta em breve…" npc="에레브" />
  <key id="s_MemoryofDragon_01" name="Nascimento… Luz…" npc="NotUse" />
  <key id="s_MemoryofDragon_02" name="Escuridão… Morte…" npc="NotUse" />
  <key id="s_MemoryofDragon_03" name="Destino…" npc="NotUse" />
  <key id="s_Cut_Blackstar_Crash_01" name="O que faz aqui? Quer morrer?" npc="흑성회원" />
  <key id="s_Cut_Blackstar_Crash_02" name="Ugh... É... É você, não é? Tudo isso só para achar\nuns idiotas? Você... Você enlouqueceu..." npc="흑성회원" />
  <key id="s_Cut_Blackstar_Crash_03" name="Você não sai daqui com vida." npc="흑성회원" />
  <key id="s_Cut_Blackstar_Crash_04" name="Nem mais um passo! O chefe quer dar uma palavrinha!" npc="흑성회원" />
  <key id="s_Cut_Blackstar_Crash_05" name="Alguém tem dado uma canseira no meu pessoal...\nMas é apenas você…" npc="웨이 홍" />
  <key id="s_Cut_Blackstar_Crash_06" name="Ha, ha, ha...\nBoas-vindas ao meu domínio." npc="웨이 홍" />
  <key id="s_KarKarIntro_01" name="O poder de invocar um dragão… \nSe eu me tornar o Kaiser, vou conquistar este mundo… Mesmo que eu precise destruí-lo." npc="바르칸트" />
  <key id="s_ProphecyofFall_01" name="Destruição pela luz..." npc="홀슈타트" />
  <key id="s_2ndjobStory_01" name="Constantemente, novas ameaças têm surgido contra o Mundo Maple." feature="JobChange_01" npc="system" />
  <key id="s_2ndjobStory_02" name="As forças das trevas viram seus olhos em direção ao império." feature="JobChange_01" npc="system" />
  <key id="s_2ndjobStory_03" name="A Fortaleza Celeste levantou voo para enfrentar esse mal." feature="JobChange_01" npc="system" />
  <key id="s_2ndjobStory_04" name="E... Infernog foi revivido." feature="JobChange_01" npc="system" />
  <key id="s_2ndjobStory_05" name="Apesar do grande perigo, os heróis do Mundo Maple se recusam a desistir." feature="JobChange_01" npc="system" />
  <key id="s_2ndjobStory_06" name="Esses heróis buscaram um novo poder para ajudar a causa deles." feature="JobChange_01" npc="system" />
  <key id="s_2ndjobStory_07" name="O poder da luz ficou ainda mais reluzente." feature="JobChange_01" npc="system" />
  <key id="s_2ndjobStory_08" name="O mundo estava mudando." feature="JobChange_01" npc="system" />
  <key id="s_2ndjobStory_09" name="E essa mudança... começa a se manifestar dentro do próprio mundo." feature="JobChange_01" npc="system" />
  <key id="s_Cut_Vivid_Dream_01" name="Depois dos últimos testes, sinais vitais estão estáveis. Nenhuma reação crítica foi detectada... \nTaxa de sincronização de 98%! Alterando os objetos para a fase 3." locale="NA" npc="칸두라 부하" />
  <key id="s_Cut_Vivid_Dream_02" name="Excelente." locale="NA" npc="칸두라" />
  <key id="s_Cut_Vivid_Dream_03" name="Você se lembra de nossa fuga? Eu não te abandonei naquele dia. Nunca." locale="NA" npc="비전" />
  <key id="s_Cut_Vivid_Dream_04" name="Não os deixem escapar! Atirem se for nescessário!" locale="NA" npc="칸두라 부하" />
  <key id="s_Cut_Vivid_Dream_05" name="Agora você nem se lembra de quem você era. Alguns detalhes são dolorosamente vívidos,\nmas o mais importante, a verdade, fica oculto por atrás de uma névoa. E se eles não tivessem te achado..." locale="NA" npc="PC 독백" />
  <key id="s_Cut_Vivid_Dream_06" name="Nosso misterioso convidado está evanescendo." locale="NA" npc="라오즈" />
  <key id="s_Cut_Vivid_Dream_07" name="Mestre! Você não pode confiar esse poder a um estranho... A um humano!" locale="NA" npc="준타" />
  <key id="s_Cut_Vivid_Dream_08" name="Este poder é a única esperança deles." locale="NA" npc="라오즈" />
  <key id="s_Cut_Vivid_Dream_09" name="Eles te deram uma nova vida, novas memórias." locale="NA" npc="PC 독백" />
  <key id="s_Cut_Vivid_Dream_10" name="Você se esqueceu da tortura que sofremos... mas tambem me esqueceu." locale="NA" npc="PC 독백" />
  <key id="s_Cut_Vivid_Dream_11" name="Seu problema é que te falta equilibrio." locale="NA" npc="준타" />
  <key id="s_Cut_Vivid_Dream_12" name="Ouça-me quando eu falo!" locale="NA" npc="준타" />
  <key id="s_Cut_Vivid_Dream_13" name="De novo, não." locale="NA" npc="준타" />
  <key id="s_Nutaman_intro_01" name="Aguardo o retorno de meu mestre..." locale="NA" feature="NutaNuta" npc="누타만" />
  <key id="s_Nutaman_intro_02" name="Quem ousa invadir este local sagrado?" locale="NA" feature="NutaNuta" npc="누타만" />
  <key id="s_KatvanIntroMovie_01" name="Aceite este presente." locale="NA" feature="KatvanDungeon" npc="마왕" />
  <key id="s_KatvanIntroMovie_02" name="Deixe-o criar raízes." locale="NA" feature="KatvanDungeon" npc="마왕" />
  <key id="s_KatvanIntroMovie_03" name="A dor vai purificar você..." locale="NA" feature="KatvanDungeon" npc="마왕" />
  <key id="s_KatvanIntroMovie_04" name="...e lhe conceder poder." locale="NA" feature="KatvanDungeon" npc="마왕" />
  <key id="s_KatvanIntroMovie_05" name="E agora você renascerá!" locale="NA" feature="KatvanDungeon" npc="마왕" />
  <key id="s_Kritias_EpicCutScene_second_01" name="The encounter with Claudia, Vanheim's daughter." feature="Kritias_Epic03" npc="system" />
  <key id="s_Kritias_EpicCutScene_second_02" name="The alliance between Humanitas and the Maple Alliance." feature="Kritias_Epic03" npc="system" />
  <key id="s_Kritias_EpicCutScene_second_03" name="Turka's death. And..." feature="Kritias_Epic03" npc="system" />
  <key id="s_Kritias_EpicCutScene_second_04" name="Her identity and even relationship with Jessica..." feature="Kritias_Epic03" npc="system" />
</ms2>