<?xml version="1.0" encoding="utf-8"?>
<!-- 파싱해서 사용하는 데이터이니 직접 수정하지 마세요 -->
<!--From : itemProperty_ETC-->
<ms2>
	<item id="59200049">
		<environment>
			<property rank="1" type="10" subtype="17" iconCode="23" slotMax="9999" category="Package" blackMarketCategory="23" doNotPreview="2" />
			<limit transferType="1" />
			<material ui="1" attack="0" />
			<function name="OpenItemBox" parameter="0,1,0,330000244" onlyShadowContinent="0" />
		</environment>
	</item>
	<item id="59200050">
		<environment>
			<property rank="1" type="10" subtype="17" iconCode="23" slotMax="9999" category="Package" blackMarketCategory="23" doNotPreview="2" />
			<limit transferType="1" />
			<material ui="1" attack="0" />
			<function name="OpenItemBox" parameter="0,1,0,330000245" onlyShadowContinent="0" />
		</environment>
	</item>
	<item id="59200051">
		<environment>
			<property rank="1" type="10" subtype="17" iconCode="23" slotMax="9999" category="Package" blackMarketCategory="23" doNotPreview="2" />
			<limit transferType="1" />
			<material ui="1" attack="0" />
			<function name="OpenItemBox" parameter="0,1,0,330000246" onlyShadowContinent="0" />
		</environment>
	</item>
	<item id="59200052">
		<environment>
			<property rank="1" type="10" subtype="17" iconCode="23" slotMax="9999" category="Package" blackMarketCategory="23" doNotPreview="2" />
			<limit transferType="1" />
			<material ui="1" attack="0" />
			<function name="OpenItemBox" parameter="0,1,0,330000247" onlyShadowContinent="0" />
		</environment>
	</item>
	<item id="59200053">
		<environment>
			<property rank="1" type="10" subtype="17" iconCode="23" slotMax="9999" category="Package" blackMarketCategory="23" doNotPreview="2" />
			<limit transferType="1" />
			<material ui="1" attack="0" />
			<function name="OpenItemBox" parameter="0,1,0,330000248" onlyShadowContinent="0" />
		</environment>
	</item>
	<item id="59200054">
		<environment>
			<property rank="1" type="10" subtype="17" iconCode="23" slotMax="9999" category="Package" blackMarketCategory="23" doNotPreview="2" />
			<limit transferType="1" />
			<material ui="1" attack="0" />
			<function name="OpenItemBox" parameter="0,1,0,330000249" onlyShadowContinent="0" />
		</environment>
	</item>
	<item id="59200055">
		<environment>
			<property rank="1" type="10" subtype="17" iconCode="23" slotMax="9999" category="Package" blackMarketCategory="23" doNotPreview="2" />
			<limit transferType="1" />
			<material ui="1" attack="0" />
			<function name="OpenItemBox" parameter="0,1,0,330000250" onlyShadowContinent="0" />
		</environment>
	</item>
	<item id="59200056">
		<environment>
			<property rank="1" type="10" subtype="17" iconCode="23" slotMax="9999" category="Package" blackMarketCategory="23" doNotPreview="2" />
			<limit transferType="1" />
			<material ui="1" attack="0" />
			<function name="OpenItemBox" parameter="0,1,0,330000251" onlyShadowContinent="0" />
		</environment>
	</item>
	<item id="59200057">
		<environment>
			<property rank="1" type="10" subtype="17" iconCode="23" slotMax="9999" category="Package" blackMarketCategory="23" doNotPreview="2" />
			<limit transferType="1" />
			<material ui="1" attack="0" />
			<function name="OpenItemBox" parameter="0,1,0,330000252" onlyShadowContinent="0" />
		</environment>
	</item>
	<item id="59200058">
		<environment>
			<property rank="1" type="10" subtype="17" iconCode="23" slotMax="9999" category="Package" blackMarketCategory="23" doNotPreview="2" />
			<limit transferType="1" />
			<material ui="1" attack="0" />
			<function name="OpenItemBox" parameter="0,1,0,330000253" onlyShadowContinent="0" />
		</environment>
	</item>
	<item id="59200059">
		<environment>
			<property rank="1" type="10" subtype="17" iconCode="23" slotMax="9999" category="Package" blackMarketCategory="23" doNotPreview="2" />
			<limit transferType="1" />
			<material ui="1" attack="0" />
			<function name="OpenItemBox" parameter="0,1,0,330000254" onlyShadowContinent="0" />
		</environment>
	</item>
	<item id="59200060">
		<environment>
			<property rank="1" type="10" subtype="17" iconCode="23" slotMax="9999" category="Package" blackMarketCategory="23" doNotPreview="2" />
			<limit transferType="1" />
			<material ui="1" attack="0" />
			<function name="OpenItemBox" parameter="0,1,0,330000255" onlyShadowContinent="0" />
		</environment>
	</item>
	<item id="59200061">
		<environment>
			<property rank="1" type="10" subtype="17" iconCode="23" slotMax="9999" category="Package" blackMarketCategory="23" doNotPreview="2" />
			<limit transferType="1" />
			<material ui="1" attack="0" />
			<function name="OpenItemBox" parameter="0,1,0,330000256" onlyShadowContinent="0" />
		</environment>
	</item>
	<item id="59200062">
		<environment>
			<property rank="1" type="10" subtype="17" iconCode="23" slotMax="9999" category="Package" blackMarketCategory="23" doNotPreview="2" />
			<limit transferType="1" />
			<material ui="1" attack="0" />
			<function name="OpenItemBox" parameter="0,1,0,330000257" onlyShadowContinent="0" />
		</environment>
	</item>
	<item id="59200063">
		<environment>
			<property rank="1" type="10" subtype="17" iconCode="23" slotMax="9999" category="Package" blackMarketCategory="23" doNotPreview="2" />
			<limit transferType="1" />
			<material ui="1" attack="0" />
			<function name="OpenItemBox" parameter="0,1,0,330000258" onlyShadowContinent="0" />
		</environment>
	</item>
	<item id="59200064">
		<environment>
			<property rank="1" type="10" subtype="17" iconCode="23" slotMax="9999" category="Package" blackMarketCategory="23" doNotPreview="2" />
			<limit transferType="1" />
			<material ui="1" attack="0" />
			<function name="OpenItemBox" parameter="0,1,0,330000259" onlyShadowContinent="0" />
		</environment>
	</item>
	<item id="59200065">
		<environment>
			<property rank="1" type="10" subtype="17" iconCode="23" slotMax="9999" category="Package" blackMarketCategory="23" doNotPreview="2" />
			<limit transferType="1" />
			<material ui="1" attack="0" />
			<function name="OpenItemBox" parameter="0,1,0,330000260" onlyShadowContinent="0" />
		</environment>
	</item>
	<item id="59200066">
		<environment>
			<property rank="1" type="10" subtype="17" iconCode="23" slotMax="9999" category="Package" blackMarketCategory="23" doNotPreview="2" />
			<limit transferType="1" />
			<material ui="1" attack="0" />
			<function name="OpenItemBox" parameter="0,1,0,330000261" onlyShadowContinent="0" />
		</environment>
	</item>
	<item id="59200067">
		<environment>
			<property rank="1" type="10" subtype="17" iconCode="23" slotMax="9999" category="Package" blackMarketCategory="23" doNotPreview="2" />
			<limit transferType="1" />
			<material ui="1" attack="0" />
			<function name="OpenItemBox" parameter="0,1,0,330000262" onlyShadowContinent="0" />
		</environment>
	</item>
	<item id="59200068">
		<environment>
			<property rank="1" type="10" subtype="17" iconCode="23" slotMax="9999" category="Package" blackMarketCategory="23" doNotPreview="2" />
			<limit transferType="1" />
			<material ui="1" attack="0" />
			<function name="OpenItemBox" parameter="0,1,0,330000263" onlyShadowContinent="0" />
		</environment>
	</item>
	<item id="59200069">
		<environment>
			<property rank="1" type="10" subtype="17" iconCode="23" slotMax="9999" category="Package" blackMarketCategory="23" doNotPreview="2" />
			<limit transferType="1" />
			<material ui="1" attack="0" />
			<function name="OpenItemBox" parameter="0,1,0,330000264" onlyShadowContinent="0" />
		</environment>
	</item>
	<item id="59200070">
		<environment>
			<property rank="1" type="10" subtype="17" iconCode="23" slotMax="9999" category="Package" blackMarketCategory="23" doNotPreview="2" />
			<limit transferType="1" />
			<material ui="1" attack="0" />
			<function name="OpenItemBox" parameter="0,1,0,330000265" onlyShadowContinent="0" />
		</environment>
	</item>
	<item id="59200071">
		<environment>
			<property rank="1" type="10" subtype="17" iconCode="23" slotMax="9999" category="Package" blackMarketCategory="23" doNotPreview="2" />
			<limit transferType="1" />
			<material ui="1" attack="0" />
			<function name="OpenItemBox" parameter="0,1,0,330000266" onlyShadowContinent="0" />
		</environment>
	</item>
	<item id="59200072">
		<environment>
			<property rank="1" type="10" subtype="17" iconCode="23" slotMax="9999" category="Package" blackMarketCategory="23" doNotPreview="2" />
			<limit transferType="1" />
			<material ui="1" attack="0" />
			<function name="OpenItemBox" parameter="0,1,0,330000267" onlyShadowContinent="0" />
		</environment>
	</item>
	<item id="59200073">
		<environment>
			<property rank="1" type="10" subtype="17" iconCode="23" slotMax="9999" category="Package" blackMarketCategory="23" doNotPreview="2" />
			<limit transferType="1" />
			<material ui="1" attack="0" />
			<function name="OpenItemBox" parameter="0,1,0,330000268" onlyShadowContinent="0" />
		</environment>
	</item>
	<item id="59200074">
		<environment>
			<property rank="1" type="10" subtype="17" iconCode="23" slotMax="9999" category="Package" blackMarketCategory="23" doNotPreview="2" />
			<limit transferType="1" />
			<material ui="1" attack="0" />
			<function name="OpenItemBox" parameter="0,1,0,330000269" onlyShadowContinent="0" />
		</environment>
	</item>
	<item id="59200075">
		<environment>
			<property rank="1" type="10" subtype="17" iconCode="23" slotMax="9999" category="Package" blackMarketCategory="23" doNotPreview="2" />
			<limit transferType="1" />
			<material ui="1" attack="0" />
			<function name="OpenItemBox" parameter="0,1,0,330000270" onlyShadowContinent="0" />
		</environment>
	</item>
	<item id="59200076">
		<environment>
			<property rank="1" type="10" subtype="17" iconCode="23" slotMax="9999" category="Package" blackMarketCategory="23" doNotPreview="2" />
			<limit transferType="1" />
			<material ui="1" attack="0" />
			<function name="OpenItemBox" parameter="0,1,0,330000271" onlyShadowContinent="0" />
		</environment>
	</item>
	<item id="59200077">
		<environment>
			<property rank="1" type="10" subtype="17" iconCode="23" slotMax="9999" category="Package" blackMarketCategory="23" doNotPreview="2" />
			<limit transferType="1" />
			<material ui="1" attack="0" />
			<function name="OpenItemBox" parameter="0,1,0,330000272" onlyShadowContinent="0" />
		</environment>
	</item>
	<item id="59200078">
		<environment>
			<property rank="1" type="10" subtype="17" iconCode="23" slotMax="9999" category="Package" blackMarketCategory="23" doNotPreview="2" />
			<limit transferType="1" />
			<material ui="1" attack="0" />
			<function name="OpenItemBox" parameter="0,1,0,330000290" onlyShadowContinent="0" />
		</environment>
	</item>
	<item id="59200079">
		<environment>
			<property rank="1" type="10" subtype="17" iconCode="23" slotMax="9999" category="Package" blackMarketCategory="23" doNotPreview="2" />
			<limit transferType="1" />
			<material ui="1" attack="0" />
			<function name="OpenItemBox" parameter="0,1,0,330000291" onlyShadowContinent="0" />
		</environment>
	</item>
	<item id="59200080">
		<environment>
			<property rank="1" type="10" subtype="17" iconCode="23" slotMax="9999" category="Package" blackMarketCategory="23" doNotPreview="2" />
			<limit transferType="1" />
			<material ui="1" attack="0" />
			<function name="OpenItemBox" parameter="0,1,0,330000292" onlyShadowContinent="0" />
		</environment>
	</item>
	<item id="59200081">
		<environment>
			<property rank="1" type="10" subtype="17" iconCode="23" slotMax="9999" category="Package" blackMarketCategory="23" doNotPreview="2" />
			<limit transferType="1" />
			<material ui="1" attack="0" />
			<function name="OpenItemBox" parameter="0,1,0,330000293" onlyShadowContinent="0" />
		</environment>
	</item>
	<item id="59200082">
		<environment>
			<property rank="1" type="10" subtype="17" iconCode="23" slotMax="9999" category="Package" blackMarketCategory="23" doNotPreview="2" />
			<limit transferType="1" />
			<material ui="1" attack="0" />
			<function name="OpenItemBox" parameter="0,1,0,330000294" onlyShadowContinent="0" />
		</environment>
	</item>
	<item id="59200083">
		<environment>
			<property rank="1" type="10" subtype="17" iconCode="23" slotMax="9999" category="Package" blackMarketCategory="23" doNotPreview="2" />
			<limit transferType="1" />
			<material ui="1" attack="0" />
			<function name="OpenItemBox" parameter="0,1,0,330000295" onlyShadowContinent="0" />
		</environment>
	</item>
	<item id="59200084">
		<environment>
			<property rank="1" type="10" subtype="17" iconCode="23" slotMax="9999" category="Package" blackMarketCategory="23" doNotPreview="2" />
			<limit transferType="1" />
			<material ui="1" attack="0" />
			<function name="OpenItemBox" parameter="0,1,0,330000296" onlyShadowContinent="0" />
		</environment>
	</item>
	<item id="59200085">
		<environment>
			<property rank="1" type="10" subtype="17" iconCode="23" slotMax="9999" category="Package" blackMarketCategory="23" doNotPreview="2" />
			<limit transferType="1" />
			<material ui="1" attack="0" />
			<function name="OpenItemBox" parameter="0,1,0,330000297" onlyShadowContinent="0" />
		</environment>
	</item>
	<item id="59200086">
		<environment>
			<property rank="1" type="10" subtype="17" iconCode="23" slotMax="9999" category="Package" blackMarketCategory="23" doNotPreview="2" />
			<limit transferType="1" />
			<material ui="1" attack="0" />
			<function name="OpenItemBox" parameter="0,1,0,330000298" onlyShadowContinent="0" />
		</environment>
	</item>
	<item id="59200087">
		<environment>
			<property rank="1" type="10" subtype="17" iconCode="23" slotMax="9999" category="Package" blackMarketCategory="23" doNotPreview="2" />
			<limit transferType="1" />
			<material ui="1" attack="0" />
			<function name="OpenItemBox" parameter="0,1,0,330000299" onlyShadowContinent="0" />
		</environment>
	</item>
	<item id="59200088">
		<environment>
			<property rank="1" type="10" subtype="17" iconCode="23" slotMax="9999" category="Package" blackMarketCategory="23" doNotPreview="2" />
			<limit transferType="1" />
			<material ui="1" attack="0" />
			<function name="OpenItemBox" parameter="0,1,0,330000300" onlyShadowContinent="0" />
		</environment>
	</item>
	<item id="59200089">
		<environment>
			<property rank="1" type="10" subtype="17" iconCode="23" slotMax="9999" category="Package" blackMarketCategory="23" doNotPreview="2" />
			<limit transferType="1" />
			<material ui="1" attack="0" />
			<function name="OpenItemBox" parameter="0,1,0,330000301" onlyShadowContinent="0" />
		</environment>
	</item>
	<item id="59200090">
		<environment>
			<property rank="1" type="10" subtype="17" iconCode="23" slotMax="9999" category="Package" blackMarketCategory="23" doNotPreview="2" />
			<limit transferType="1" />
			<material ui="1" attack="0" />
			<function name="OpenItemBox" parameter="0,1,0,330000302" onlyShadowContinent="0" />
		</environment>
	</item>
	<item id="59200091">
		<environment>
			<property rank="1" type="10" subtype="17" iconCode="23" slotMax="9999" category="Package" blackMarketCategory="23" doNotPreview="2" />
			<limit transferType="1" />
			<material ui="1" attack="0" />
			<function name="OpenItemBox" parameter="0,1,0,330000303" onlyShadowContinent="0" />
		</environment>
	</item>
	<item id="59200092">
		<environment>
			<property rank="1" type="10" subtype="17" iconCode="23" slotMax="9999" category="Package" blackMarketCategory="23" doNotPreview="2" />
			<limit transferType="1" />
			<material ui="1" attack="0" />
			<function name="OpenItemBox" parameter="0,1,0,330000304" onlyShadowContinent="0" />
		</environment>
	</item>
	<item id="59200093">
		<environment>
			<property rank="1" type="10" subtype="17" iconCode="23" slotMax="9999" category="Package" blackMarketCategory="23" doNotPreview="2" />
			<limit transferType="1" />
			<material ui="1" attack="0" />
			<function name="OpenItemBox" parameter="0,1,0,330000305" onlyShadowContinent="0" />
		</environment>
	</item>
	<item id="59200094">
		<environment>
			<property rank="1" type="10" subtype="17" iconCode="23" slotMax="9999" category="Package" blackMarketCategory="23" doNotPreview="2" />
			<limit transferType="1" />
			<material ui="1" attack="0" />
			<function name="OpenItemBox" parameter="0,1,0,330000306" onlyShadowContinent="0" />
		</environment>
	</item>
	<item id="59200095">
		<environment>
			<property rank="1" type="10" subtype="17" iconCode="23" slotMax="9999" category="Package" blackMarketCategory="23" doNotPreview="2" />
			<limit transferType="1" />
			<material ui="1" attack="0" />
			<function name="OpenItemBox" parameter="0,1,0,330000307" onlyShadowContinent="0" />
		</environment>
	</item>
	<item id="59200096">
		<environment>
			<property rank="1" type="10" subtype="17" iconCode="23" slotMax="9999" category="Package" blackMarketCategory="23" doNotPreview="2" />
			<limit transferType="1" />
			<material ui="1" attack="0" />
			<function name="OpenItemBox" parameter="0,1,0,330000308" onlyShadowContinent="0" />
		</environment>
	</item>
	<item id="59200097">
		<environment>
			<property rank="1" type="10" subtype="17" iconCode="23" slotMax="9999" category="Package" blackMarketCategory="23" doNotPreview="2" />
			<limit transferType="1" />
			<material ui="1" attack="0" />
			<function name="OpenItemBox" parameter="0,1,0,330000309" onlyShadowContinent="0" />
		</environment>
	</item>
	<item id="59200098">
		<environment>
			<property rank="1" type="10" subtype="17" iconCode="23" slotMax="9999" category="Package" blackMarketCategory="23" doNotPreview="2" />
			<limit transferType="1" />
			<material ui="1" attack="0" />
			<function name="OpenItemBox" parameter="0,1,0,330000310" onlyShadowContinent="0" />
		</environment>
	</item>
	<item id="59200099">
		<environment>
			<property rank="1" type="10" subtype="17" iconCode="23" slotMax="9999" category="Package" blackMarketCategory="23" doNotPreview="2" />
			<limit transferType="1" />
			<material ui="1" attack="0" />
			<function name="OpenItemBox" parameter="0,1,0,330000311" onlyShadowContinent="0" />
		</environment>
	</item>
	<item id="59200100">
		<environment>
			<property rank="1" type="10" subtype="17" iconCode="23" slotMax="9999" category="Package" blackMarketCategory="23" doNotPreview="2" />
			<limit transferType="1" />
			<material ui="1" attack="0" />
			<function name="OpenItemBox" parameter="0,1,0,330000312" onlyShadowContinent="0" />
		</environment>
	</item>
	<item id="59200101">
		<environment>
			<property rank="1" type="10" subtype="17" iconCode="23" slotMax="9999" category="Package" blackMarketCategory="23" doNotPreview="2" />
			<limit transferType="1" />
			<material ui="1" attack="0" />
			<function name="OpenItemBox" parameter="0,1,0,330000313" onlyShadowContinent="0" />
		</environment>
	</item>
	<item id="59200102">
		<environment>
			<property rank="1" type="10" subtype="17" iconCode="23" slotMax="9999" category="Package" blackMarketCategory="23" doNotPreview="2" />
			<limit transferType="1" />
			<material ui="1" attack="0" />
			<function name="OpenItemBox" parameter="0,1,0,330000314" onlyShadowContinent="0" />
		</environment>
	</item>
	<item id="59200103">
		<environment>
			<property rank="1" type="10" subtype="17" iconCode="23" slotMax="9999" category="Package" blackMarketCategory="23" doNotPreview="2" />
			<limit transferType="1" />
			<material ui="1" attack="0" />
			<function name="OpenItemBox" parameter="0,1,0,330000315" onlyShadowContinent="0" />
		</environment>
	</item>
	<item id="59200104">
		<environment>
			<property rank="1" type="10" subtype="17" iconCode="23" slotMax="9999" category="Package" blackMarketCategory="23" doNotPreview="2" />
			<limit transferType="1" />
			<material ui="1" attack="0" />
			<function name="OpenItemBox" parameter="0,1,0,330000316" onlyShadowContinent="0" />
		</environment>
	</item>
	<item id="59200105">
		<environment>
			<property rank="1" type="10" subtype="17" iconCode="23" slotMax="9999" category="Package" blackMarketCategory="23" doNotPreview="2" />
			<limit transferType="1" />
			<material ui="1" attack="0" />
			<function name="OpenItemBox" parameter="0,1,0,330000317" onlyShadowContinent="0" />
		</environment>
	</item>
	<item id="59200106">
		<environment>
			<property rank="1" type="10" subtype="17" iconCode="23" slotMax="9999" category="Package" blackMarketCategory="23" doNotPreview="2" />
			<limit transferType="1" />
			<material ui="1" attack="0" />
			<function name="OpenItemBox" parameter="0,1,0,330000318" onlyShadowContinent="0" />
		</environment>
	</item>
	<item id="59200107">
		<environment>
			<property rank="1" type="10" subtype="17" iconCode="23" slotMax="9999" category="Package" blackMarketCategory="23" doNotPreview="2" />
			<limit transferType="1" />
			<material ui="1" attack="0" />
			<function name="OpenItemBox" parameter="0,1,0,330000319" onlyShadowContinent="0" />
		</environment>
	</item>
	<item id="59200108">
		<environment>
			<property rank="1" type="10" subtype="17" iconCode="23" slotMax="9999" category="Package" blackMarketCategory="23" doNotPreview="2" />
			<limit transferType="1" />
			<material ui="1" attack="0" />
			<function name="OpenItemBox" parameter="0,1,0,330000320" onlyShadowContinent="0" />
		</environment>
	</item>
	<item id="59200109">
		<environment>
			<property rank="1" type="10" subtype="17" iconCode="23" slotMax="9999" category="Package" blackMarketCategory="23" doNotPreview="2" />
			<limit transferType="1" />
			<material ui="1" attack="0" />
			<function name="OpenItemBox" parameter="0,1,0,330000321" onlyShadowContinent="0" />
		</environment>
	</item>
	<item id="59200110">
		<environment>
			<property rank="1" type="10" subtype="17" iconCode="23" slotMax="9999" category="Package" blackMarketCategory="23" doNotPreview="2" />
			<limit transferType="1" />
			<material ui="1" attack="0" />
			<function name="OpenItemBox" parameter="0,1,0,330000322" onlyShadowContinent="0" />
		</environment>
	</item>
	<item id="59200111">
		<environment>
			<property rank="1" type="10" subtype="17" iconCode="23" slotMax="9999" category="Package" blackMarketCategory="23" doNotPreview="2" />
			<limit transferType="1" />
			<material ui="1" attack="0" />
			<function name="OpenItemBox" parameter="0,1,0,330000323" onlyShadowContinent="0" />
		</environment>
	</item>
	<item id="59200112">
		<environment>
			<property rank="1" type="10" subtype="17" iconCode="23" slotMax="9999" category="Package" blackMarketCategory="23" doNotPreview="2" />
			<limit transferType="1" />
			<material ui="1" attack="0" />
			<function name="OpenItemBox" parameter="0,1,0,330000324" onlyShadowContinent="0" />
		</environment>
	</item>
	<item id="59200113">
		<environment>
			<property rank="1" type="10" subtype="17" iconCode="23" slotMax="9999" category="Package" blackMarketCategory="23" doNotPreview="2" />
			<limit transferType="1" />
			<material ui="1" attack="0" />
			<function name="OpenItemBox" parameter="0,1,0,330000325" onlyShadowContinent="0" />
		</environment>
	</item>
	<item id="59200114">
		<environment>
			<property rank="1" type="10" subtype="17" iconCode="23" slotMax="9999" category="Package" blackMarketCategory="23" doNotPreview="2" />
			<limit transferType="1" />
			<material ui="1" attack="0" />
			<function name="OpenItemBox" parameter="0,1,0,330000326" onlyShadowContinent="0" />
		</environment>
	</item>
	<item id="59200115">
		<environment>
			<property rank="1" type="10" subtype="17" iconCode="23" slotMax="9999" category="Package" blackMarketCategory="23" doNotPreview="2" />
			<limit transferType="1" />
			<material ui="1" attack="0" />
			<function name="OpenItemBox" parameter="0,1,0,330000327" onlyShadowContinent="0" />
		</environment>
	</item>
	<item id="59200116">
		<environment>
			<property rank="1" type="10" subtype="17" iconCode="23" slotMax="9999" category="Package" blackMarketCategory="23" doNotPreview="2" />
			<limit transferType="1" />
			<material ui="1" attack="0" />
			<function name="OpenItemBox" parameter="0,1,0,330000328" onlyShadowContinent="0" />
		</environment>
	</item>
	<item id="59200117">
		<environment>
			<property rank="1" type="10" subtype="17" iconCode="23" slotMax="9999" category="Package" blackMarketCategory="23" doNotPreview="2" />
			<limit transferType="1" />
			<material ui="1" attack="0" />
			<function name="OpenItemBox" parameter="0,1,0,330000329" onlyShadowContinent="0" />
		</environment>
	</item>
	<item id="59200118">
		<environment>
			<property rank="1" type="10" subtype="17" iconCode="23" slotMax="9999" category="Package" blackMarketCategory="23" doNotPreview="2" />
			<limit transferType="1" />
			<material ui="1" attack="0" />
			<function name="OpenItemBox" parameter="0,1,0,330000330" onlyShadowContinent="0" />
		</environment>
	</item>
	<item id="59200119">
		<environment>
			<property rank="1" type="10" subtype="17" iconCode="23" slotMax="9999" category="Package" blackMarketCategory="23" doNotPreview="2" />
			<limit transferType="1" />
			<material ui="1" attack="0" />
			<function name="OpenItemBox" parameter="0,1,0,330000331" onlyShadowContinent="0" />
		</environment>
	</item>
	<item id="59200120">
		<environment>
			<property rank="1" type="10" subtype="17" iconCode="23" slotMax="9999" category="Package" blackMarketCategory="23" doNotPreview="2" />
			<limit transferType="1" />
			<material ui="1" attack="0" />
			<function name="OpenItemBox" parameter="0,1,0,330000332" onlyShadowContinent="0" />
		</environment>
	</item>
	<item id="59200121">
		<environment>
			<property rank="1" type="10" subtype="17" iconCode="23" slotMax="9999" category="Package" blackMarketCategory="23" doNotPreview="2" />
			<limit transferType="1" />
			<material ui="1" attack="0" />
			<function name="OpenItemBox" parameter="0,1,0,330000333" onlyShadowContinent="0" />
		</environment>
	</item>
	<item id="59200122">
		<environment>
			<property rank="1" type="10" subtype="17" iconCode="23" slotMax="9999" category="Package" blackMarketCategory="23" doNotPreview="2" />
			<limit transferType="1" />
			<material ui="1" attack="0" />
			<function name="OpenItemBox" parameter="0,1,0,330000334" onlyShadowContinent="0" />
		</environment>
	</item>
	<item id="59200123">
		<environment>
			<property rank="1" type="10" subtype="17" iconCode="23" slotMax="9999" category="Package" blackMarketCategory="23" doNotPreview="2" />
			<limit transferType="1" />
			<material ui="1" attack="0" />
			<function name="OpenItemBox" parameter="0,1,0,330000335" onlyShadowContinent="0" />
		</environment>
	</item>
	<item id="59200124">
		<environment>
			<property rank="1" type="10" subtype="17" iconCode="23" slotMax="9999" category="Package" blackMarketCategory="23" doNotPreview="2" />
			<limit transferType="1" />
			<material ui="1" attack="0" />
			<function name="OpenItemBox" parameter="0,1,0,330000336" onlyShadowContinent="0" />
		</environment>
	</item>
	<item id="59200125">
		<environment>
			<property rank="1" type="10" subtype="17" iconCode="23" slotMax="9999" category="Package" blackMarketCategory="23" doNotPreview="2" />
			<limit transferType="1" />
			<material ui="1" attack="0" />
			<function name="OpenItemBox" parameter="0,1,0,330000337" onlyShadowContinent="0" />
		</environment>
	</item>
	<item id="59200126">
		<environment>
			<property rank="1" type="10" subtype="17" iconCode="23" slotMax="9999" category="Package" blackMarketCategory="23" doNotPreview="2" />
			<limit transferType="1" />
			<material ui="1" attack="0" />
			<function name="OpenItemBox" parameter="0,1,0,330000338" onlyShadowContinent="0" />
		</environment>
	</item>
	<item id="59200127">
		<environment>
			<property rank="1" type="10" subtype="17" iconCode="23" slotMax="9999" category="Package" blackMarketCategory="23" doNotPreview="2" />
			<limit transferType="1" />
			<material ui="1" attack="0" />
			<function name="OpenItemBox" parameter="0,1,0,330000339" onlyShadowContinent="0" />
		</environment>
	</item>
	<item id="59200128">
		<environment>
			<property rank="1" type="10" subtype="17" iconCode="23" slotMax="9999" category="Package" blackMarketCategory="23" doNotPreview="2" />
			<limit transferType="1" />
			<material ui="1" attack="0" />
			<function name="OpenItemBox" parameter="0,1,0,330000340" onlyShadowContinent="0" />
		</environment>
	</item>
	<item id="59200129">
		<environment>
			<property rank="1" type="10" subtype="17" iconCode="23" slotMax="9999" category="Package" blackMarketCategory="23" doNotPreview="2" />
			<limit transferType="1" />
			<material ui="1" attack="0" />
			<function name="OpenItemBox" parameter="0,1,0,330000341" onlyShadowContinent="0" />
		</environment>
	</item>
	<item id="59200130">
		<environment>
			<property rank="1" type="10" subtype="17" iconCode="23" slotMax="9999" category="Package" blackMarketCategory="23" doNotPreview="2" />
			<limit transferType="1" />
			<material ui="1" attack="0" />
			<function name="OpenItemBox" parameter="0,1,0,330000342" onlyShadowContinent="0" />
		</environment>
	</item>
	<item id="59200131">
		<environment>
			<property rank="1" type="10" subtype="17" iconCode="23" slotMax="9999" category="Package" blackMarketCategory="23" doNotPreview="2" />
			<limit transferType="1" />
			<material ui="1" attack="0" />
			<function name="OpenItemBox" parameter="0,1,0,330000343" onlyShadowContinent="0" />
		</environment>
	</item>
	<item id="59200132">
		<environment>
			<property rank="1" type="10" subtype="17" iconCode="23" slotMax="9999" category="Package" blackMarketCategory="23" doNotPreview="2" />
			<limit transferType="1" />
			<material ui="1" attack="0" />
			<function name="OpenItemBox" parameter="0,1,0,330000344" onlyShadowContinent="0" />
		</environment>
	</item>
	<item id="59200133">
		<environment>
			<property rank="1" type="10" subtype="17" iconCode="23" slotMax="9999" category="Package" blackMarketCategory="23" doNotPreview="2" />
			<limit transferType="1" />
			<material ui="1" attack="0" />
			<function name="OpenItemBox" parameter="0,1,0,330000345" onlyShadowContinent="0" />
		</environment>
	</item>
	<item id="59200134">
		<environment>
			<property rank="1" type="10" subtype="17" iconCode="23" slotMax="9999" category="Package" blackMarketCategory="23" doNotPreview="2" />
			<limit transferType="1" />
			<material ui="1" attack="0" />
			<function name="OpenItemBox" parameter="0,1,0,330000346" onlyShadowContinent="0" />
		</environment>
	</item>
	<item id="59200135">
		<environment>
			<property rank="1" type="10" subtype="17" iconCode="23" slotMax="9999" category="Package" blackMarketCategory="23" doNotPreview="2" />
			<limit transferType="1" />
			<material ui="1" attack="0" />
			<function name="OpenItemBox" parameter="0,1,0,330000347" onlyShadowContinent="0" />
		</environment>
	</item>
	<item id="59200136">
		<environment>
			<property rank="1" type="10" subtype="17" iconCode="23" slotMax="9999" category="Package" blackMarketCategory="23" doNotPreview="2" />
			<limit transferType="1" />
			<material ui="1" attack="0" />
			<function name="OpenItemBox" parameter="0,1,0,330000348" onlyShadowContinent="0" />
		</environment>
	</item>
	<item id="59200137">
		<environment>
			<property rank="1" type="10" subtype="17" iconCode="23" slotMax="9999" category="Package" blackMarketCategory="23" doNotPreview="2" />
			<limit transferType="1" />
			<material ui="1" attack="0" />
			<function name="OpenItemBox" parameter="0,1,0,330000349" onlyShadowContinent="0" />
		</environment>
	</item>
	<item id="59200138">
		<environment>
			<property rank="1" type="10" subtype="17" iconCode="23" slotMax="9999" category="Package" blackMarketCategory="23" doNotPreview="2" />
			<limit transferType="1" />
			<material ui="1" attack="0" />
			<function name="OpenItemBox" parameter="0,1,0,330000350" onlyShadowContinent="0" />
		</environment>
	</item>
	<item id="59200139">
		<environment>
			<property rank="1" type="10" subtype="17" iconCode="23" slotMax="9999" category="Package" blackMarketCategory="23" doNotPreview="2" />
			<limit transferType="1" />
			<material ui="1" attack="0" />
			<function name="OpenItemBox" parameter="0,1,0,330000351" onlyShadowContinent="0" />
		</environment>
	</item>
	<item id="59200140">
		<environment>
			<property rank="1" type="10" subtype="17" iconCode="23" slotMax="9999" category="Package" blackMarketCategory="23" doNotPreview="2" />
			<limit transferType="1" />
			<material ui="1" attack="0" />
			<function name="OpenItemBox" parameter="0,1,0,330000352" onlyShadowContinent="0" />
		</environment>
	</item>
	<item id="59200141">
		<environment>
			<property rank="1" type="10" subtype="17" iconCode="23" slotMax="9999" category="Package" blackMarketCategory="23" doNotPreview="2" />
			<limit transferType="1" />
			<material ui="1" attack="0" />
			<function name="OpenItemBox" parameter="0,1,0,330000353" onlyShadowContinent="0" />
		</environment>
	</item>
	<item id="59200142">
		<environment>
			<property rank="1" type="10" subtype="17" iconCode="23" slotMax="9999" category="Package" blackMarketCategory="23" doNotPreview="2" />
			<limit transferType="1" />
			<material ui="1" attack="0" />
			<function name="OpenItemBox" parameter="0,1,0,330000354" onlyShadowContinent="0" />
		</environment>
	</item>
	<item id="59200143">
		<environment>
			<property rank="1" type="10" subtype="17" iconCode="23" slotMax="9999" category="Package" blackMarketCategory="23" doNotPreview="2" />
			<limit transferType="1" />
			<material ui="1" attack="0" />
			<function name="OpenItemBox" parameter="0,1,0,330000355" onlyShadowContinent="0" />
		</environment>
	</item>
	<item id="59200144">
		<environment>
			<property rank="1" type="10" subtype="17" iconCode="23" slotMax="9999" category="Package" blackMarketCategory="23" doNotPreview="2" />
			<limit transferType="1" />
			<material ui="1" attack="0" />
			<function name="OpenItemBox" parameter="0,1,0,330000356" onlyShadowContinent="0" />
		</environment>
	</item>
	<item id="59200145">
		<environment>
			<property rank="1" type="10" subtype="17" iconCode="23" slotMax="9999" category="Package" blackMarketCategory="23" doNotPreview="2" />
			<limit transferType="1" />
			<material ui="1" attack="0" />
			<function name="OpenItemBox" parameter="0,1,0,330000357" onlyShadowContinent="0" />
		</environment>
	</item>
	<item id="59200146">
		<environment>
			<property rank="1" type="10" subtype="17" iconCode="23" slotMax="9999" category="Package" blackMarketCategory="23" doNotPreview="2" />
			<limit transferType="1" />
			<material ui="1" attack="0" />
			<function name="OpenItemBox" parameter="0,1,0,330000358" onlyShadowContinent="0" />
		</environment>
	</item>
	<item id="59200147">
		<environment>
			<property rank="1" type="10" subtype="17" iconCode="23" slotMax="9999" category="Package" blackMarketCategory="23" doNotPreview="2" />
			<limit transferType="1" />
			<material ui="1" attack="0" />
			<function name="OpenItemBox" parameter="0,1,0,330000359" onlyShadowContinent="0" />
		</environment>
	</item>
	<item id="59200148">
		<environment>
			<property rank="1" type="10" subtype="17" iconCode="23" slotMax="9999" category="Package" blackMarketCategory="23" doNotPreview="2" />
			<limit transferType="1" />
			<material ui="1" attack="0" />
			<function name="OpenItemBox" parameter="0,1,0,330000360" onlyShadowContinent="0" />
		</environment>
	</item>
	<item id="59200149">
		<environment>
			<property rank="1" type="10" subtype="17" iconCode="23" slotMax="9999" category="Package" blackMarketCategory="23" doNotPreview="2" />
			<limit transferType="1" />
			<material ui="1" attack="0" />
			<function name="OpenItemBox" parameter="0,1,0,330000361" onlyShadowContinent="0" />
		</environment>
	</item>
	<item id="59200150">
		<environment>
			<property rank="1" type="10" subtype="17" iconCode="23" slotMax="9999" category="Package" blackMarketCategory="23" doNotPreview="2" />
			<limit transferType="1" />
			<material ui="1" attack="0" />
			<function name="OpenItemBox" parameter="0,1,0,330000362" onlyShadowContinent="0" />
		</environment>
	</item>
	<item id="59200151">
		<environment>
			<property rank="1" type="10" subtype="17" iconCode="23" slotMax="9999" category="Package" blackMarketCategory="23" doNotPreview="2" />
			<limit transferType="1" />
			<material ui="1" attack="0" />
			<function name="OpenItemBox" parameter="0,1,0,330000363" onlyShadowContinent="0" />
		</environment>
	</item>
	<item id="59200152">
		<environment>
			<property rank="1" type="10" subtype="17" iconCode="23" slotMax="9999" category="Package" blackMarketCategory="23" doNotPreview="2" />
			<limit transferType="1" />
			<material ui="1" attack="0" />
			<function name="OpenItemBox" parameter="0,1,0,330000364" onlyShadowContinent="0" />
		</environment>
	</item>
	<item id="59200153">
		<environment>
			<property rank="1" type="10" subtype="17" iconCode="23" slotMax="9999" category="Package" blackMarketCategory="23" doNotPreview="2" />
			<limit transferType="1" />
			<material ui="1" attack="0" />
			<function name="OpenItemBox" parameter="0,1,0,330000365" onlyShadowContinent="0" />
		</environment>
	</item>
	<item id="59200154">
		<environment>
			<property rank="1" type="10" subtype="17" iconCode="23" slotMax="9999" category="Package" blackMarketCategory="23" doNotPreview="2" />
			<limit transferType="1" />
			<material ui="1" attack="0" />
			<function name="OpenItemBox" parameter="0,1,0,330000366" onlyShadowContinent="0" />
		</environment>
	</item>
	<item id="59200155">
		<environment>
			<property rank="1" type="10" subtype="17" iconCode="23" slotMax="9999" category="Package" blackMarketCategory="23" doNotPreview="2" />
			<limit transferType="1" />
			<material ui="1" attack="0" />
			<function name="OpenItemBox" parameter="0,1,0,330000367" onlyShadowContinent="0" />
		</environment>
	</item>
	<item id="59200156">
		<environment>
			<property rank="1" type="10" subtype="17" iconCode="23" slotMax="9999" category="Package" blackMarketCategory="23" doNotPreview="2" />
			<limit transferType="1" />
			<material ui="1" attack="0" />
			<function name="OpenItemBox" parameter="0,1,0,330000368" onlyShadowContinent="0" />
		</environment>
	</item>
	<item id="59200157">
		<environment>
			<property rank="1" type="10" subtype="17" iconCode="23" slotMax="9999" category="Package" blackMarketCategory="23" doNotPreview="2" />
			<limit transferType="1" />
			<material ui="1" attack="0" />
			<function name="OpenItemBox" parameter="0,1,0,330000369" onlyShadowContinent="0" />
		</environment>
	</item>
	<item id="59200158">
		<environment>
			<property rank="1" type="10" subtype="17" iconCode="23" slotMax="9999" category="Package" blackMarketCategory="23" doNotPreview="2" />
			<limit transferType="1" />
			<material ui="1" attack="0" />
			<function name="OpenItemBox" parameter="0,1,0,330000370" onlyShadowContinent="0" />
		</environment>
	</item>
	<item id="59200159">
		<environment>
			<property rank="1" type="10" subtype="17" iconCode="23" slotMax="9999" category="Package" blackMarketCategory="23" doNotPreview="2" />
			<limit transferType="1" />
			<material ui="1" attack="0" />
			<function name="OpenItemBox" parameter="0,1,0,330000371" onlyShadowContinent="0" />
		</environment>
	</item>
	<item id="59200160">
		<environment>
			<property rank="1" type="10" subtype="17" iconCode="23" slotMax="9999" category="Package" blackMarketCategory="23" doNotPreview="2" />
			<limit transferType="1" />
			<material ui="1" attack="0" />
			<function name="OpenItemBox" parameter="0,1,0,330000372" onlyShadowContinent="0" />
		</environment>
	</item>
	<item id="59200161">
		<environment>
			<property rank="1" type="10" subtype="17" iconCode="23" slotMax="9999" category="Package" blackMarketCategory="23" doNotPreview="2" />
			<limit transferType="1" />
			<material ui="1" attack="0" />
			<function name="OpenItemBox" parameter="0,1,0,330000388" onlyShadowContinent="0" />
		</environment>
	</item>
	<item id="59200162">
		<environment>
			<property rank="1" type="10" subtype="18" iconCode="24" slotMax="9999" category="Package" blackMarketCategory="24" doNotPreview="2" />
			<life expirationPeriod="2015-10-22-23-59-59" />
			<limit transferType="1" />
			<material ui="1" attack="0" />
			<function name="OpenItemBox" parameter="0,1,0,330000382" onlyShadowContinent="0" />
		</environment>
	</item>
	<item id="59200163">
		<environment>
			<property rank="1" type="10" subtype="18" iconCode="24" slotMax="9999" category="Package" blackMarketCategory="24" doNotPreview="2" />
			<life expirationPeriod="2015-10-22-23-59-59" />
			<limit transferType="1" />
			<material ui="1" attack="0" />
			<function name="OpenItemBox" parameter="0,1,0,330000383" onlyShadowContinent="0" />
		</environment>
	</item>
	<item id="59200164">
		<environment>
			<property rank="1" type="10" subtype="18" iconCode="24" slotMax="9999" category="Package" blackMarketCategory="24" doNotPreview="2" />
			<life expirationPeriod="2015-10-22-23-59-59" />
			<limit transferType="1" />
			<material ui="1" attack="0" />
			<function name="OpenItemBox" parameter="0,1,0,330000384" onlyShadowContinent="0" />
		</environment>
	</item>
	<item id="59200179">
		<environment>
			<property rank="1" type="10" subtype="18" iconCode="23" slotMax="9999" slotIcon="59200050" category="Package" blackMarketCategory="23" doNotPreview="2" />
			<limit transferType="2" />
			<material ui="1" attack="0" />
			<function name="OpenItemBox" parameter="0,1,0,330000407" onlyShadowContinent="0" />
		</environment>
	</item>
	<item id="59200180">
		<environment>
			<property rank="1" type="10" subtype="18" iconCode="9" slotMax="9999" category="Package" blackMarketCategory="9" doNotPreview="2" />
			<limit transferType="2" />
			<material ui="1" attack="0" />
			<function name="OpenItemBox" parameter="0,1,0,330000421" onlyShadowContinent="0" />
		</environment>
	</item>
	<item id="59200181">
		<environment>
			<property rank="1" type="10" subtype="18" iconCode="9" slotMax="9999" category="Package" blackMarketCategory="9" doNotPreview="2" />
			<limit transferType="2" />
			<material ui="1" attack="0" />
			<function name="OpenItemBox" parameter="0,1,0,330000420" onlyShadowContinent="0" />
		</environment>
	</item>
	<item id="59200182">
		<environment>
			<property rank="1" type="10" subtype="18" iconCode="9" slotMax="9999" category="Package" blackMarketCategory="9" doNotPreview="2" />
			<limit transferType="2" />
			<material ui="1" attack="0" />
			<function name="OpenItemBox" parameter="0,1,0,330000419" onlyShadowContinent="0" />
		</environment>
	</item>
	<item id="59200184">
		<environment>
			<property rank="1" type="10" subtype="18" iconCode="9" slotMax="9999" category="Package" blackMarketCategory="9" doNotPreview="2" />
			<limit transferType="1" />
			<material ui="1" attack="0" />
			<function name="OpenItemBox" parameter="0,1,0,330000425" onlyShadowContinent="0" />
		</environment>
	</item>
	<item id="59200185">
		<environment>
			<property rank="1" type="10" subtype="18" iconCode="23" slotMax="9999" category="Package" blackMarketCategory="23" doNotPreview="2" />
			<limit transferType="6" />
			<material ui="1" attack="0" />
			<function name="OpenItemBox" parameter="0,1,0,330000426" onlyShadowContinent="0" />
		</environment>
	</item>
	<item id="59200186">
		<environment>
			<property rank="1" type="10" subtype="18" iconCode="23" slotMax="9999" category="Package" blackMarketCategory="23" doNotPreview="2" />
			<limit transferType="6" />
			<material ui="1" attack="0" />
			<function name="OpenItemBox" parameter="0,1,0,330000427" onlyShadowContinent="0" />
		</environment>
	</item>
	<item id="59200189">
		<environment>
			<property rank="1" type="10" subtype="17" iconCode="23" slotMax="9999" slotIcon="59200049" category="Package" blackMarketCategory="23" doNotPreview="2" />
			<life usePeriod="43200" />
			<limit transferType="1" />
			<material ui="1" attack="0" />
			<function name="OpenItemBox" parameter="0,1,0,330000441" onlyShadowContinent="0" />
		</environment>
	</item>
	<item id="59200190">
		<environment>
			<property rank="1" type="10" subtype="17" iconCode="23" slotMax="9999" slotIcon="59200049" category="Package" blackMarketCategory="23" doNotPreview="2" />
			<life usePeriod="43200" />
			<limit transferType="1" />
			<material ui="1" attack="0" />
			<function name="OpenItemBox" parameter="0,1,0,330000442" onlyShadowContinent="0" />
		</environment>
	</item>
	<item id="59200191">
		<environment>
			<property rank="1" type="10" subtype="17" iconCode="23" slotMax="9999" slotIcon="59200050" category="Package" blackMarketCategory="23" doNotPreview="2" />
			<life usePeriod="43200" />
			<limit transferType="1" />
			<material ui="1" attack="0" />
			<function name="OpenItemBox" parameter="0,1,0,330000443" onlyShadowContinent="0" />
		</environment>
	</item>
	<item id="59200192">
		<environment>
			<property rank="1" type="10" subtype="17" iconCode="23" slotMax="9999" slotIcon="59200051" category="Package" blackMarketCategory="23" doNotPreview="2" />
			<life usePeriod="43200" />
			<limit transferType="1" />
			<material ui="1" attack="0" />
			<function name="OpenItemBox" parameter="0,1,0,330000444" onlyShadowContinent="0" />
		</environment>
	</item>
	<item id="59200199">
		<environment>
			<property rank="1" type="10" subtype="18" iconCode="23" slotMax="9999" category="Package" blackMarketCategory="23" doNotPreview="2" />
			<limit transferType="1" />
			<material ui="1" attack="0" />
			<function name="OpenItemBox" parameter="0,1,0,330000479" onlyShadowContinent="0" />
		</environment>
	</item>
	<item id="59200200">
		<environment>
			<property rank="1" type="10" subtype="18" iconCode="23" slotMax="9999" category="Package" blackMarketCategory="23" doNotPreview="2" />
			<limit transferType="1" />
			<material ui="1" attack="0" />
			<function name="OpenItemBox" parameter="0,1,0,330000480" onlyShadowContinent="0" />
		</environment>
	</item>
	<item id="59200201">
		<environment>
			<property rank="1" type="10" subtype="18" iconCode="23" slotMax="9999" category="Package" blackMarketCategory="23" doNotPreview="2" />
			<limit transferType="1" />
			<material ui="1" attack="0" />
			<function name="OpenItemBox" parameter="0,1,0,330000481" onlyShadowContinent="0" />
		</environment>
	</item>
	<item id="59200202">
		<environment>
			<property rank="1" type="10" subtype="18" iconCode="23" slotMax="9999" category="Package" blackMarketCategory="23" doNotPreview="2" />
			<limit transferType="1" />
			<material ui="1" attack="0" />
			<function name="OpenItemBox" parameter="0,1,0,330000482" onlyShadowContinent="0" />
		</environment>
	</item>
</ms2>