<?xml version="1.0" encoding="utf-8"?>
<ms2>
	<seq id="0" name="Attack_01_C">
		<key name="end" time="1.5000" />
	</seq>
	<seq id="1" name="Attack_01_A">
		<key name="p0" time="0.1290" />
		<key name="move0" time="0.6289" />
		<key name="move1" time="0.8800" />
		<key name="p1" time="1.3990" />
		<key name="end" time="2.4000" />
	</seq>
	<seq id="2" name="Dead_A">
		<key name="end" time="16.1333" />
	</seq>
	<seq id="3" name="Stun_A">
		<key name="end" time="1.4667" />
	</seq>
	<seq id="4" name="Attack_02_D">
		<key name="move0" time="0.0522" />
		<key name="move1" time="0.4049" />
		<key name="end" time="0.4667" />
	</seq>
	<seq id="5" name="Attack_02_E">
		<key name="p0" time="0.0173" />
		<key name="end" time="0.5667" />
	</seq>
	<seq id="6" name="Run_A">
		<key name="end" time="0.6000" />
	</seq>
	<seq id="7" name="Attack_02_F">
		<key name="end" time="0.2000" />
	</seq>
	<seq id="8" name="Attack_02_G">
		<key name="p0" time="0.1900" />
		<key name="end" time="0.5000" />
	</seq>
	<seq id="9" name="Talk_A">
		<key name="end" time="4.6667" />
	</seq>
	<seq id="10" name="Attack_03_D">
		<key name="p0" time="1.8008" />
		<key name="move0" time="1.8092" />
		<key name="move1" time="2.4548" />
		<key name="end" time="6.0000" />
	</seq>
	<seq id="11" name="Attack_03_E">
		<key name="p0" time="0.0329" />
		<key name="end" time="1.5000" />
	</seq>
	<seq id="12" name="Attack_03_F">
		<key name="p0" time="0.2419" />
		<key name="p1" time="0.4234" />
		<key name="p2" time="0.5881" />
		<key name="p3" time="0.7258" />
		<key name="p4" time="0.8797" />
		<key name="p5" time="1.0553" />
		<key name="p6" time="1.2259" />
		<key name="p7" time="1.6056" />
		<key name="end" time="1.8000" />
		<key name="move0" time="1.8000" />
		<key name="move1" time="2.2333" />
	</seq>
	<seq id="13" name="Attack_03_G">
		<key name="end" time="2.2000" />
	</seq>
	<seq id="14" name="Dead_Idle_A">
		<key name="end" time="2.4667" />
	</seq>
	<seq id="15" name="Attack_04_E">
		<key name="p0" time="0.0448" />
		<key name="move0" time="0.0475" />
		<key name="move1" time="0.4452" />
		<key name="end" time="1.6000" />
	</seq>
	<seq id="16" name="Attack_03_C">
		<key name="p0" time="0.1628" />
		<key name="p1" time="0.5840" />
		<key name="end" time="1.6333" />
	</seq>
	<seq id="17" name="Attack_04_F">
		<key name="end" time="3.6000" />
	</seq>
	<seq id="18" name="Attack_01_H">
		<key name="move0" time="0.6666" />
		<key name="move1" time="0.8100" />
		<key name="p0" time="0.8260" />
		<key name="end" time="1.1333" />
	</seq>
	<seq id="19" name="Attack_02_H">
		<key name="move0" time="0.1333" />
		<key name="p0" time="0.5300" />
		<key name="move1" time="0.5333" />
		<key name="end" time="1.4333" />
	</seq>
	<seq id="20" name="DashAttack_01_A">
		<key name="end" time="0.6667" />
	</seq>
	<seq id="21" name="DashAttack_02_A">
		<key name="move0" time="0.0233" />
		<key name="move1" time="0.1298" />
		<key name="end" time="0.1333" />
	</seq>
	<seq id="22" name="DashAttack_03_A">
		<key name="move0" time="0.0145" />
		<key name="p0" time="0.0321" />
		<key name="mvoe1" time="0.3464" />
		<key name="end" time="0.8667" />
	</seq>
	<seq id="23" name="Attack_04_G">
		<key name="p0" time="1.5700" />
		<key name="end" time="3.1000" />
	</seq>
	<seq id="24" name="Attack_01_D">
		<key name="end" time="2.0000" />
	</seq>
	<seq id="25" name="Attack_01_E">
		<key name="end" time="2.5000" />
	</seq>
	<seq id="26" name="Attack_01_F">
		<key name="end" time="2.0000" />
	</seq>
	<seq id="27" name="Attack_01_G">
		<key name="end" time="2.0000" />
	</seq>
	<seq id="28" name="Attack_02_C">
		<key name="p0" time="0.1628" />
		<key name="end" time="1.3000" />
	</seq>
	<seq id="29" name="Attack_01_B">
		<key name="p0" time="0.1790" />
		<key name="p1" time="0.3736" />
		<key name="end" time="1.0667" />
	</seq>
	<seq id="30" name="Attack_Idle_A">
		<key name="end" time="0.9333" />
	</seq>
</ms2>