<?xml version="1.0" encoding="utf-8"?>
<!-- 파싱해서 사용하는 데이터이니 직접 수정하지 마세요 -->
<ms2>
	<minimap>
		<image name="./Data/Resource/Image/Map/Minimap/02000114.dds" left="552.75" right="1576.75" top="97" bottom="1121" icon=".\Data\Resource\Image\Map\Icon\" />
		<frustum left="-7449.58" right="7449.58" top="4655.99" bottom="-4655.99" near="10" far="100000" ortho="true" />
		<screen left="0" right="1920" top="0" bottom="1200" />
		<camera position="-7838.980469, -4586.683594, 9884.938477" rotation="90.000000, 45.000000, -45.000000" />
		<edit zoomfactor="3.87999" />
	</minimap>
	<fog color="150,200,250" near="1000" far="9600" />
	<clientProperty bgDay="BG_Henesys_A.dds" />
</ms2>